jblibaws/__init__.py
jblibaws/aws/__init__.py
jblibaws/aws/cognito.py
jblibaws/aws/dynamodb.py
jblibaws/aws/secretsManager.py
jblibaws/dict_tools/__init__.py
jblibaws/dict_tools/dict_tools.py
jblibaws-1.2.80.dist-info/LICENSE
jblibaws-1.2.80.dist-info/METADATA
jblibaws-1.2.80.dist-info/WHEEL
jblibaws-1.2.80.dist-info/top_level.txt
jblibaws-1.2.80.dist-info/RECORD
