Metadata-Version: 2.1
Name: jblibaws
Version: 1.2.80
Summary: JustBard's Python based AWS Utilities
Home-page: https://justbardtech.com
Author: Justin Bard
Author-email: JustinBard@gmail.com
Classifier: Programming Language :: Python :: 3
Classifier: License :: OSI Approved :: MIT License
Classifier: Operating System :: POSIX :: Linux
License-File: LICENSE
